LICENSE
MANIFEST.in
README.md
setup.py
django_squirrel.egg-info/PKG-INFO
django_squirrel.egg-info/SOURCES.txt
django_squirrel.egg-info/dependency_links.txt
django_squirrel.egg-info/requires.txt
django_squirrel.egg-info/top_level.txt
docs/README.md
squirrel/__init__.py
squirrel/apps.py
squirrel/commands.py
squirrel/connections.py
squirrel/consumers.py
squirrel/contexts.py
squirrel/drones.py
squirrel/events.py
squirrel/exceptions.py
squirrel/fields.py
squirrel/firewalls.py
squirrel/forms.py
squirrel/helpers.py
squirrel/loops.py
squirrel/middleware.py
squirrel/process.py
squirrel/publishers.py
squirrel/requests.py
squirrel/responses.py
squirrel/routers.py
squirrel/routes.py
squirrel/rules.py
squirrel/settings.py
squirrel/sq_types.py
squirrel/tests.py
squirrel/urls.py
squirrel/utils.py
squirrel/views.py
squirrel/z1.py
squirrel/management/__init__.py
squirrel/management/commands/__init__.py
squirrel/management/commands/get_server_info.py
squirrel/management/commands/ping.py
squirrel/management/commands/run_server.py
squirrel/management/commands/transfers_drone.py