Metadata-Version: 2.1
Name: django-squirrel
Version: 0.2.17
Summary: Background workers based on rabbit-mq integration.
Home-page: https://gitlab.com/jo-salgado/django-squirrel
Author: Jose Salgado
Author-email: jose.salgado.wrk@gmail.com
License: BSD License
Platform: UNKNOWN
Classifier: Environment :: Web Environment
Classifier: Framework :: Django
Classifier: Framework :: Django :: 2.2
Classifier: Intended Audience :: Developers
Classifier: License :: OSI Approved :: BSD License
Classifier: Operating System :: OS Independent
Classifier: Programming Language :: Python
Classifier: Programming Language :: Python :: 3.6
Classifier: Topic :: Internet :: WWW/HTTP
Classifier: Topic :: Internet :: WWW/HTTP :: Dynamic Content
